hoa_tools/__init__.py
hoa_tools/_n5.py
hoa_tools/_version.py
hoa_tools/dataset.py
hoa_tools/inventory.py
hoa_tools/metadata.py
hoa_tools/py.typed
hoa_tools/registration.py
hoa_tools/types.py
hoa_tools/voi.py
hoa_tools/data/metadata/metadata/A129_lung_VOI-02_2.0um_bm18.json
hoa_tools/data/metadata/metadata/A186_lung_right_VOI-3_4.26um_bm18.json
hoa_tools/data/metadata/metadata/A186_lung_right_complete-organ_24.132um_bm18.json
hoa_tools/data/metadata/metadata/AUMC-005_uterus_complete-organ_20.026um_bm18.json
hoa_tools/data/metadata/metadata/FO-20-124_lung_upper_lobe_VOI-01_2.5um_bm05.json
hoa_tools/data/metadata/metadata/FO-20-124_lung_upper_lobe_VOI-01_6.5um_bm05.json
hoa_tools/data/metadata/metadata/FO-20-124_lung_upper_lobe_VOI-02_2.5um_bm05.json
hoa_tools/data/metadata/metadata/FO-20-124_lung_upper_lobe_VOI-02_6.5um_bm05.json
hoa_tools/data/metadata/metadata/FO-20-124_lung_upper_lobe_VOI-03_2.5um_bm05.json
hoa_tools/data/metadata/metadata/FO-20-124_lung_upper_lobe_VOI-03_6.5um_bm05.json
hoa_tools/data/metadata/metadata/FO-20-124_lung_upper_lobe_VOI-04_6.5um_bm05.json
hoa_tools/data/metadata/metadata/FO-20-124_lung_upper_lobe_VOI-07_2.5um_bm05.json
hoa_tools/data/metadata/metadata/FO-20-124_lung_upper_lobe_VOI-08_2.5um_bm05.json
hoa_tools/data/metadata/metadata/FO-20-124_lung_upper_lobe_central-column_6.24um_bm05.json
hoa_tools/data/metadata/metadata/FO-20-124_lung_upper_lobe_complete-organ_26.38um_bm05.json
hoa_tools/data/metadata/metadata/FO-20-125_lung_complete-organ_26.38um_bm05.json
hoa_tools/data/metadata/metadata/FO-20-129_lung_left_upper_lobe_VOI-01.2_2.22um_bm05.json
hoa_tools/data/metadata/metadata/FO-20-129_lung_left_upper_lobe_VOI-01.2b_2.22um_bm05.json
hoa_tools/data/metadata/metadata/FO-20-129_lung_left_upper_lobe_VOI-01_6.24um_bm05.json
hoa_tools/data/metadata/metadata/FO-20-129_lung_left_upper_lobe_VOI-02.2_2.22um_bm05.json
hoa_tools/data/metadata/metadata/FO-20-129_lung_left_upper_lobe_VOI-02_6.24um_bm05.json
hoa_tools-1.1.1.dist-info/licenses/LICENSE.md
hoa_tools-1.1.1.dist-info/METADATA
hoa_tools-1.1.1.dist-info/WHEEL
hoa_tools-1.1.1.dist-info/top_level.txt
hoa_tools-1.1.1.dist-info/RECORD
