Metadata-Version: 2.4
Name: hoa-tools
Version: 1.1.1
Summary: Tools for working with the Human Organ Atlas
Author-email: David Stansby <d.stansby@ucl.ac.uk>
License: Copyright (c) 2024, David Stansby
Project-URL: homepage, https://github.com/HumanOrganAtlas/hoa-tools
Classifier: Operating System :: POSIX
Classifier: Programming Language :: Python :: 3
Classifier: Programming Language :: Python :: 3 :: Only
Classifier: Programming Language :: Python :: 3.11
Classifier: Programming Language :: Python :: 3.12
Classifier: Programming Language :: Python :: 3.13
Classifier: Typing :: Typed
Requires-Python: >=3.11
License-File: LICENSE.md
Requires-Dist: dask[array]
Requires-Dist: gcsfs>2023
Requires-Dist: networkx>=3
Requires-Dist: pandas>=2
Requires-Dist: pydantic>=2
Requires-Dist: simpleitk
Requires-Dist: xarray
Requires-Dist: zarr>=3
Provides-Extra: dev
Requires-Dist: build; extra == "dev"
Requires-Dist: mypy; extra == "dev"
Requires-Dist: pre-commit; extra == "dev"
Requires-Dist: ruff; extra == "dev"
Requires-Dist: jupyterlab; extra == "dev"
Requires-Dist: jupytext; extra == "dev"
Requires-Dist: types-networkx; extra == "dev"
Requires-Dist: pandas-stubs; extra == "dev"
Requires-Dist: datamodel-code-generator; extra == "dev"
Provides-Extra: docs
Requires-Dist: mkdocs; extra == "docs"
Requires-Dist: mkdocstrings-python; extra == "docs"
Requires-Dist: mkdocs-material; extra == "docs"
Requires-Dist: mkdocs-jupyter; extra == "docs"
Requires-Dist: griffe-pydantic; extra == "docs"
Requires-Dist: matplotlib; extra == "docs"
Requires-Dist: numpydoc; extra == "docs"
Requires-Dist: scikit-image; extra == "docs"
Provides-Extra: test
Requires-Dist: matplotlib; extra == "test"
Requires-Dist: pytest; extra == "test"
Requires-Dist: pytest-accept; extra == "test"
Requires-Dist: pytest-cov; extra == "test"
Requires-Dist: pytest-doctestplus; extra == "test"
Requires-Dist: pytest-vcr; extra == "test"
Requires-Dist: scikit-image; extra == "test"
Dynamic: license-file
